[
  {
    "id": "fade22cc-632f-44f1-b495-a31e96a867a2",
    "image": "/certificados/1775067938675-Captura_de_tela_20260401_095811.png",
    "text": "INTRODUÇÃO A MACHINE LEARNING EM PYTHON "
  },
  {
    "id": "3cc012e1-dabb-4e5b-bcbb-08bb1850f2e0",
    "image": "/certificados/1775068046987-dsa.png",
    "text": "Fundamentos de Linguagem Python Para Análise de Dados, Data Science e Machine Learning"
  },
  {
    "id": "b8f17fc9-c8b5-4cd1-a83e-e77cb739ae62",
    "image": "/certificados/1775068124571-dsa.png",
    "text": "IMERSÃO DE IA 3° EDIÇÃO"
  }
]